{"env":{"runId":"run_SYLtGjFUSREitQhdhWjhZ","ok":true,"status":200,"latencyMs":31243,"payment":{"protocol":"x402","chain":"base","txHash":"0xac0edd7c99398b2aa71592d2f11aa19dc72da699b2ea0ccaa26996b854b90262","amount":"0.007","asset":"USDC"},"body":{"output":{"found":true,"data":{"items":[{"inputProfileName":"David Cramer","social":"askfm","socialProfileUrl":null},{"inputProfileName":"David Cramer","social":"discord","socialProfileUrl":null},{"inputProfileName":"David Cramer","social":"facebook","socialProfileUrl":"https://www.facebook.com/david.cramer.10236"}]}},"provider":"AnyAPI","costUsd":0.007,"items":3},"bodyRaw":"{\"output\":{\"found\":true,\"data\":{\"items\":[{\"inputProfileName\":\"David Cramer\",\"social\":\"askfm\",\"socialProfileUrl\":null},{\"inputProfileName\":\"David Cramer\",\"social\":\"discord\",\"socialProfileUrl\":null},{\"inputProfileName\":\"David Cramer\",\"social\":\"facebook\",\"socialProfileUrl\":\"https://www.facebook.com/david.cramer.10236\"}]}},\"provider\":\"AnyAPI\",\"costUsd\":0.007,\"items\":3}\n"},"latencyMs":32374,"savedAt":"2026-07-17T19:01:22.846Z"}