{"env":{"runId":"run_pymAZvTRkLOnnJdxRu5fa","ok":true,"status":200,"latencyMs":1690,"payment":{"protocol":"x402","chain":"base","txHash":"0x2392b8db5810edcf1ea4ec8b1a043d6ed21b1ff325a835485bce83741fb1fb5e","amount":"0.001","asset":"USDC"},"body":{"data":{"ok":true,"items":[{"login":"rauchg","name":"Guillermo Rauch","company":"https://vercel.com","blog":"http://twitter.com/rauchg","location":"SF","bio":null,"type":"User","followers":16991,"following":882,"publicRepos":140,"publicGists":31,"createdAt":"2008-06-09T02:22:48Z","url":"https://github.com/rauchg"}],"total":1,"source":{"provider":"GitHub","url":"https://github.com","license":"GitHub REST API; redistributed read-only."}},"meta":{"endpoint":"github.user","version":null,"caller":"x402","cost":{"usd":0.001},"settlement":{"txHash":"0x2392b8db5810edcf1ea4ec8b1a043d6ed21b1ff325a835485bce83741fb1fb5e","network":"eip155:8453","success":true}}},"bodyRaw":"{\"data\":{\"ok\":true,\"items\":[{\"login\":\"rauchg\",\"name\":\"Guillermo Rauch\",\"company\":\"https://vercel.com\",\"blog\":\"http://twitter.com/rauchg\",\"location\":\"SF\",\"bio\":null,\"type\":\"User\",\"followers\":16991,\"following\":882,\"publicRepos\":140,\"publicGists\":31,\"createdAt\":\"2008-06-09T02:22:48Z\",\"url\":\"https://github.com/rauchg\"}],\"total\":1,\"source\":{\"provider\":\"GitHub\",\"url\":\"https://github.com\",\"license\":\"GitHub REST API; redistributed read-only.\"}},\"meta\":{\"endpoint\":\"github.user\",\"version\":null,\"caller\":\"x402\",\"cost\":{\"usd\":0.001},\"settlement\":{\"txHash\":\"0x2392b8db5810edcf1ea4ec8b1a043d6ed21b1ff325a835485bce83741fb1fb5e\",\"network\":\"eip155:8453\",\"success\":true}}}"},"latencyMs":2552,"savedAt":"2026-07-17T19:36:47.848Z"}